LICENSE
MANIFEST.in
README.rst
setup.cfg
setup.py
doc/Makefile
doc/changelog.rst
doc/classes.rst
doc/conf.py
doc/index.rst
doc/_static/yield.png
doc/examples/index.rst
examples/__init__.py
examples/example.py
test/__init__.py
test/async_test_engine.py
test/test_yieldpoints.py
yieldpoints/__init__.py
yieldpoints.egg-info/PKG-INFO
yieldpoints.egg-info/SOURCES.txt
yieldpoints.egg-info/dependency_links.txt
yieldpoints.egg-info/requires.txt
yieldpoints.egg-info/top_level.txt